py_date_utils/__init__.py
py_date_utils-0.0.1.dist-info/LICENSE
py_date_utils-0.0.1.dist-info/METADATA
py_date_utils-0.0.1.dist-info/WHEEL
py_date_utils-0.0.1.dist-info/RECORD
